litesimple.py
setup.py
litesimple.egg-info/PKG-INFO
litesimple.egg-info/SOURCES.txt
litesimple.egg-info/dependency_links.txt
litesimple.egg-info/top_level.txt