Metadata-Version: 1.1
Name: litesimple
Version: 0.1.0
Summary: Simple python ORM micro-framework for sqlite3
Home-page: https://github.com/TheThing/litesimple
Author: Jonatan Nilsson
Author-email: jonatan@nilsson.is
License: WTFPL-2
Platform: UNKNOWN
Classifier: Development Status :: 3 - Alpha
Classifier: Environment :: Plugins
Classifier: Environment :: Web Environment
Classifier: Intended Audience :: Developers
Classifier: License :: OSI Approved :: BSD License
Classifier: Operating System :: OS Independent
Classifier: Programming Language :: Python
Classifier: Topic :: Database
Classifier: Topic :: Software Development
Classifier: Topic :: Software Development :: Libraries
